ourprojects/__init__.py
ourprojects/models.py
ourprojects/migrations/0001_initial.py
ourprojects/migrations/0002_lamindbv1.py
ourprojects/migrations/0003_alter_person_space_alter_project_space_and_more.py
ourprojects/migrations/__init__.py
ourprojects-1.0.1.dist-info/LICENSE
ourprojects-1.0.1.dist-info/WHEEL
ourprojects-1.0.1.dist-info/METADATA
ourprojects-1.0.1.dist-info/RECORD
